{"name":"build-javascript","namedChunkGroups":{"polyfill":{"name":"polyfill","assets":[{"name":"webpack-runtime-7cca06c6834c2488cb24.js","size":4146},{"name":"polyfill-b227d9031ab4094e5021.js","size":85856}],"filteredAssets":0,"assetsSize":90002,"filteredAuxiliaryAssets":2,"auxiliaryAssetsSize":224140},"app":{"name":"app","assets":[{"name":"webpack-runtime-7cca06c6834c2488cb24.js","size":4146},{"name":"framework-e413e527015be9a1bdfd.js","size":129760},{"name":"styles.3061f950ccd1a77d8eec.css","size":17646},{"name":"app-1516daf8d6a7315b19ca.js","size":111599}],"filteredAssets":0,"assetsSize":263151,"filteredAuxiliaryAssets":55,"auxiliaryAssetsSize":1903031},"component---src-pages-404-js":{"name":"component---src-pages-404-js","assets":[{"name":"cb1608f2-f84de5122df4c289695d.js","size":975},{"name":"a9a7754c-7a045e64f413fa6946a6.js","size":2561},{"name":"commons-95dc7e3f01651fea51b3.js","size":23360},{"name":"component---src-pages-404-js-e980ce90d527f1b6247b.js","size":550}],"filteredAssets":0,"assetsSize":27446,"filteredAuxiliaryAssets":4,"auxiliaryAssetsSize":1316240},"component---src-pages-index-js":{"name":"component---src-pages-index-js","assets":[{"name":"cb1608f2-f84de5122df4c289695d.js","size":975},{"name":"a9a7754c-7a045e64f413fa6946a6.js","size":2561},{"name":"commons-95dc7e3f01651fea51b3.js","size":23360},{"name":"component---src-pages-index-js-822b5faecd0b576da913.js","size":1567}],"filteredAssets":0,"assetsSize":28463,"filteredAuxiliaryAssets":4,"auxiliaryAssetsSize":1319395},"component---src-pages-using-typescript-tsx":{"name":"component---src-pages-using-typescript-tsx","assets":[{"name":"cb1608f2-f84de5122df4c289695d.js","size":975},{"name":"a9a7754c-7a045e64f413fa6946a6.js","size":2561},{"name":"commons-95dc7e3f01651fea51b3.js","size":23360},{"name":"component---src-pages-using-typescript-tsx-172bf71d7850ee7f3e84.js","size":1372}],"filteredAssets":0,"assetsSize":28268,"filteredAuxiliaryAssets":4,"auxiliaryAssetsSize":1317386},"component---src-templates-blog-post-js":{"name":"component---src-templates-blog-post-js","assets":[{"name":"cb1608f2-f84de5122df4c289695d.js","size":975},{"name":"a9a7754c-7a045e64f413fa6946a6.js","size":2561},{"name":"commons-95dc7e3f01651fea51b3.js","size":23360},{"name":"component---src-templates-blog-post-js-3ab3619d936f4ad08395.js","size":1426}],"filteredAssets":0,"assetsSize":28322,"filteredAuxiliaryAssets":4,"auxiliaryAssetsSize":1319558}},"assetsByChunkName":{"polyfill":["webpack-runtime-7cca06c6834c2488cb24.js","polyfill-b227d9031ab4094e5021.js"],"app":["webpack-runtime-7cca06c6834c2488cb24.js","framework-e413e527015be9a1bdfd.js","styles.3061f950ccd1a77d8eec.css","app-1516daf8d6a7315b19ca.js"],"component---src-pages-404-js":["cb1608f2-f84de5122df4c289695d.js","a9a7754c-7a045e64f413fa6946a6.js","commons-95dc7e3f01651fea51b3.js","component---src-pages-404-js-e980ce90d527f1b6247b.js"],"component---src-pages-index-js":["cb1608f2-f84de5122df4c289695d.js","a9a7754c-7a045e64f413fa6946a6.js","commons-95dc7e3f01651fea51b3.js","component---src-pages-index-js-822b5faecd0b576da913.js"],"component---src-pages-using-typescript-tsx":["cb1608f2-f84de5122df4c289695d.js","a9a7754c-7a045e64f413fa6946a6.js","commons-95dc7e3f01651fea51b3.js","component---src-pages-using-typescript-tsx-172bf71d7850ee7f3e84.js"],"component---src-templates-blog-post-js":["cb1608f2-f84de5122df4c289695d.js","a9a7754c-7a045e64f413fa6946a6.js","commons-95dc7e3f01651fea51b3.js","component---src-templates-blog-post-js-3ab3619d936f4ad08395.js"]},"childAssetsByChunkName":{}}